pyeach/__init__.py
pyeach/eaconstants.py
pyeach/eadb.py
pyeach/eageo.py
pyeach/eastats.py
pyeach/eawrangle.py
pyeach/data/aggregate_housing_locations.txt
pyeach/data/cnp_locations.txt
pyeach/data/comm_care_locations.txt
pyeach/data/comm_food_locations.txt
pyeach/data/ed_uc_locations.txt
pyeach/data/hospital_locations.txt
pyeach/data/pcp_locations.txt
pyeach/extras/__init__.py
pyeach/extras/loaders.py
pyeach/extras/module_tests.py
pyeach-0.1.2.dist-info/METADATA
pyeach-0.1.2.dist-info/WHEEL
pyeach-0.1.2.dist-info/licenses/LICENSE
pyeach-0.1.2.dist-info/RECORD
