Metadata-Version: 2.3
Name: pyeach
Version: 0.1.2
Summary: A Cone Health Enterprise Analytics package.
Project-URL: Homepage, https://conehealth-ea@dev.azure.com/conehealth-ea/EA%20Data%20Science/_git/pyeach
Author-email: Tyler Ursuy <tyler.ursuy@conehealth.com>, Luke Brantley <luke.brantley@conehealth.com>
License-File: LICENSE
Classifier: License :: OSI Approved :: MIT License
Classifier: Operating System :: OS Independent
Classifier: Programming Language :: Python :: 3
Requires-Python: >=3.8
Requires-Dist: arviz
Requires-Dist: contextily
Requires-Dist: folium
Requires-Dist: geopandas
Requires-Dist: matplotlib
Requires-Dist: numpy
Requires-Dist: pandas
Requires-Dist: pygris
Requires-Dist: pyodbc
Requires-Dist: pyshp
Requires-Dist: scipy
Requires-Dist: sodapy
Requires-Dist: urllib3==1.26.6
